[
    {
        "subdivision_category": "province",
        "iso_3166_2_code": "DO-02",
        "subdivision_name": "Azua",
        "abbrevation": "02"
    },
    {
        "subdivision_category": "province",
        "iso_3166_2_code": "DO-03",
        "subdivision_name": "Baoruco",
        "abbrevation": "03"
    },
    {
        "subdivision_category": "province",
        "iso_3166_2_code": "DO-04",
        "subdivision_name": "Barahona",
        "abbrevation": "04"
    },
    {
        "subdivision_category": "region",
        "iso_3166_2_code": "DO-33",
        "subdivision_name": "Cibao Nordeste",
        "abbrevation": "33"
    },
    {
        "subdivision_category": "region",
        "iso_3166_2_code": "DO-34",
        "subdivision_name": "Cibao Noroeste",
        "abbrevation": "34"
    },
    {
        "subdivision_category": "region",
        "iso_3166_2_code": "DO-35",
        "subdivision_name": "Cibao Norte",
        "abbrevation": "35"
    },
    {
        "subdivision_category": "region",
        "iso_3166_2_code": "DO-36",
        "subdivision_name": "Cibao Sur",
        "abbrevation": "36"
    },
    {
        "subdivision_category": "province",
        "iso_3166_2_code": "DO-05",
        "subdivision_name": "Dajabón",
        "abbrevation": "05"
    },
    {
        "subdivision_category": "district",
        "iso_3166_2_code": "DO-01",
        "subdivision_name": "Distrito Nacional (Santo Domingo)",
        "abbrevation": "01"
    },
    {
        "subdivision_category": "province",
        "iso_3166_2_code": "DO-06",
        "subdivision_name": "Duarte",
        "abbrevation": "06"
    },
    {
        "subdivision_category": "province",
        "iso_3166_2_code": "DO-08",
        "subdivision_name": "El Seibo",
        "abbrevation": "08"
    },
    {
        "subdivision_category": "region",
        "iso_3166_2_code": "DO-37",
        "subdivision_name": "El Valle",
        "abbrevation": "37"
    },
    {
        "subdivision_category": "province",
        "iso_3166_2_code": "DO-07",
        "subdivision_name": "Elías Piña",
        "abbrevation": "07"
    },
    {
        "subdivision_category": "region",
        "iso_3166_2_code": "DO-38",
        "subdivision_name": "Enriquillo",
        "abbrevation": "38"
    },
    {
        "subdivision_category": "province",
        "iso_3166_2_code": "DO-09",
        "subdivision_name": "Espaillat",
        "abbrevation": "09"
    },
    {
        "subdivision_category": "province",
        "iso_3166_2_code": "DO-30",
        "subdivision_name": "Hato Mayor",
        "abbrevation": "30"
    },
    {
        "subdivision_category": "province",
        "iso_3166_2_code": "DO-19",
        "subdivision_name": "Hermanas Mirabal",
        "abbrevation": "19"
    },
    {
        "subdivision_category": "region",
        "iso_3166_2_code": "DO-39",
        "subdivision_name": "Higuamo",
        "abbrevation": "39"
    },
    {
        "subdivision_category": "province",
        "iso_3166_2_code": "DO-10",
        "subdivision_name": "Independencia",
        "abbrevation": "10"
    },
    {
        "subdivision_category": "province",
        "iso_3166_2_code": "DO-11",
        "subdivision_name": "La Altagracia",
        "abbrevation": "11"
    },
    {
        "subdivision_category": "province",
        "iso_3166_2_code": "DO-12",
        "subdivision_name": "La Romana",
        "abbrevation": "12"
    },
    {
        "subdivision_category": "province",
        "iso_3166_2_code": "DO-13",
        "subdivision_name": "La Vega",
        "abbrevation": "13"
    },
    {
        "subdivision_category": "province",
        "iso_3166_2_code": "DO-14",
        "subdivision_name": "María Trinidad Sánchez",
        "abbrevation": "14"
    },
    {
        "subdivision_category": "province",
        "iso_3166_2_code": "DO-28",
        "subdivision_name": "Monseñor Nouel",
        "abbrevation": "28"
    },
    {
        "subdivision_category": "province",
        "iso_3166_2_code": "DO-15",
        "subdivision_name": "Monte Cristi",
        "abbrevation": "15"
    },
    {
        "subdivision_category": "province",
        "iso_3166_2_code": "DO-29",
        "subdivision_name": "Monte Plata",
        "abbrevation": "29"
    },
    {
        "subdivision_category": "region",
        "iso_3166_2_code": "DO-40",
        "subdivision_name": "Ozama",
        "abbrevation": "40"
    },
    {
        "subdivision_category": "province",
        "iso_3166_2_code": "DO-16",
        "subdivision_name": "Pedernales",
        "abbrevation": "16"
    },
    {
        "subdivision_category": "province",
        "iso_3166_2_code": "DO-17",
        "subdivision_name": "Peravia",
        "abbrevation": "17"
    },
    {
        "subdivision_category": "province",
        "iso_3166_2_code": "DO-18",
        "subdivision_name": "Puerto Plata",
        "abbrevation": "18"
    },
    {
        "subdivision_category": "province",
        "iso_3166_2_code": "DO-20",
        "subdivision_name": "Samaná",
        "abbrevation": "20"
    },
    {
        "subdivision_category": "province",
        "iso_3166_2_code": "DO-21",
        "subdivision_name": "San Cristóbal",
        "abbrevation": "21"
    },
    {
        "subdivision_category": "province",
        "iso_3166_2_code": "DO-31",
        "subdivision_name": "San José de Ocoa",
        "abbrevation": "31"
    },
    {
        "subdivision_category": "province",
        "iso_3166_2_code": "DO-22",
        "subdivision_name": "San Juan",
        "abbrevation": "22"
    },
    {
        "subdivision_category": "province",
        "iso_3166_2_code": "DO-23",
        "subdivision_name": "San Pedro de Macorís",
        "abbrevation": "23"
    },
    {
        "subdivision_category": "province",
        "iso_3166_2_code": "DO-25",
        "subdivision_name": "Santiago",
        "abbrevation": "25"
    },
    {
        "subdivision_category": "province",
        "iso_3166_2_code": "DO-26",
        "subdivision_name": "Santiago Rodríguez",
        "abbrevation": "26"
    },
    {
        "subdivision_category": "province",
        "iso_3166_2_code": "DO-32",
        "subdivision_name": "Santo Domingo",
        "abbrevation": "32"
    },
    {
        "subdivision_category": "province",
        "iso_3166_2_code": "DO-24",
        "subdivision_name": "Sánchez Ramírez",
        "abbrevation": "24"
    },
    {
        "subdivision_category": "region",
        "iso_3166_2_code": "DO-41",
        "subdivision_name": "Valdesia",
        "abbrevation": "41"
    },
    {
        "subdivision_category": "province",
        "iso_3166_2_code": "DO-27",
        "subdivision_name": "Valverde",
        "abbrevation": "27"
    },
    {
        "subdivision_category": "region",
        "iso_3166_2_code": "DO-42",
        "subdivision_name": "Yuma",
        "abbrevation": "42"
    }
]